  {
    "$schema": "https://schema.management.azure.com/schemas/2019-04-01/deploymentTemplate.json#",
    "contentVersion": "1.0.0.0",
    "parameters": {
      "virtualNetworkName": {
        "type": "string",
        "defaultValue": "vn-security",
        "metadata": {
          "description": "Name of the Virtual Network (VNET)"
        }
      },
      "virtualNetworkAddressPrefixes": {
      "type": "array",
      "defaultValue": ["10.0.0.0/16"],
      "metadata": {
      "description": "Virtual network address CIDR"
        }
      },
      "mgmtSubnetName": {
        "type": "string",
        "defaultValue": "sn-mgmt",
        "metadata": {
          "description": "Subnet for Management"
        }
      },
      "externalSubnetName": {
        "type": "string",
        "defaultValue": "sn-external",
        "metadata": {
          "description": "Subnet for External"
        }
      },
      "internalSubnetName": {
        "type": "string",
        "defaultValue": "sn-internal",
        "metadata": {
          "description": "Subnet for Internal"
        }
      },
      "mgmtSubnetPrefix": {
        "type": "string",
        "defaultValue": "10.0.0.64/28",
        "metadata": {
          "description": "Mgmt subnet CIDR"
        }
      },
      "externalSubnetPrefix": {
        "type": "string",
        "defaultValue": "10.0.0.16/28",
        "metadata": {
          "description": "External subnet CIDR"
        }
      },
      "internalSubnetPrefix": {
        "type": "string",
        "defaultValue": "10.0.0.0/28",
        "metadata": {
          "description": "EXISTING internal subnet CIDR"
        }
      }
    },
    "variables": {

      "virtualNetworkAddressPrefix": "[parameters('virtualNetworkAddressPrefixes')[0]]",

      "subnets": [
        {
          "name": "[parameters('mgmtSubnetName')]",
          "properties": {
            "addressPrefix": "[parameters('mgmtSubnetPrefix')]"
          }
        },
        {
          "name": "[parameters('externalSubnetName')]",
          "properties": {
            "addressPrefix": "[parameters('externalSubnetPrefix')]"
          }
        },
        {
          "name": "[parameters('internalSubnetName')]",
          "properties": {
            "addressPrefix": "[parameters('internalSubnetPrefix')]"
          }
        }
      ]     
    },

    "resources": [
      {
        "name": "[parameters('virtualNetworkName')]",
        "type": "Microsoft.Network/virtualNetworks",
        "apiVersion": "2017-10-01",
        "dependsOn": [],
        "location": "[resourceGroup().location]",
        "properties": {
          "addressSpace": {
              "addressPrefixes": [
                  "[variables('virtualNetworkAddressPrefix')]"
                  ]
          },
            "subnets": "[variables('subnets')]"
        }
      }
    ]
  }